{"code":1,"data":{"programinfo":{"programid":"16","categoryid":"1","programname":"总编辑时间","programlogo":"http://imgs.diantai.ifeng.com/images/programimg/f8e3eb0ff0324b38e17763ae1663050a.jpg","programlogo2":"http://y1.ifengimg.com/FM/images/programimg/58d9aa4306e36860c4b9525b44b250f8.jpg","thumbimg":"http://y1.ifengimg.com/FM/images/programimg/58d9aa4306e36860c4b9525b44b250f8.jpg","postnum":"0","listennum":1721601,"status":"0","channelid":"1","channelname":"新闻","lastupdated_at":"1408115116","favnum":44656,"compere":"吕宁思","info":"《总编辑时间》以局内人视野解读一天中世界最值得注意的头条新闻，让你把握天下大势的脉络，在一天过去之前，来一个全面透彻的总结。由凤凰资深的评论员或总编辑重点编选和剖析重点要闻，夹播夹评、分析梳理，以总编辑清晰的思路、丰富的历史背景资料和精辟的分析能力，解构事情的来龙去脉和对日后发展的重要性，令观众可以快速抓住事情的关键，看出未来趋势。","source":"","chargeActualType":"0","android_chargeActualFee":"0.00","ios_chargeActualFee":"0.00","ios_productid":"","chargeActualFee":"0.00","isfav":0,"batchDownload":1,"totalnum":"645","isbuy":0},"totalCount":"680","audiolist":[{"title":"2014-08-15总编辑时间 快播公司总经理王欣逃往境外110天后被捕","createdTime":"2014-08-15 22:57:00","duration":1543,"order":"125217","updated_at":"1408115116","smallimgpath":"http://d.ifengimg.com/w120_h90/y0.ifengimg.com/pmop/2014/08/15/a20633cb-9ccf-4c2e-9c3f-40e340b8f172.jpg","bigimgpath":"http://d.ifengimg.com/w480_h360/y0.ifengimg.com/pmop/2014/08/15/a20633cb-9ccf-4c2e-9c3f-40e340b8f172.jpg","listennum":"11599","downloadnum":"569","commentnum":"0","isvideo":"1","videoplayurl":"http://ips.ifeng.com/3gs.ifeng.com/userfiles/video02/2014/08/15/2197212-280-068-2302.mp4","channelid":"1","channelid2":"0","categoryid":"1","programid":"16","programname":"总编辑时间","programlogo":"http://imgs.diantai.ifeng.com/images/programimg/f8e3eb0ff0324b38e17763ae1663050a.jpg","uradio":"0","favnum":44656,"watchingnum":"0","lastupdated_at":"1408115116","allowTrialplay":"1","source":"osmop","collectnum":"0","compere":"吕宁思","resourcenum":"645","commenturl":"http://diantai.ifeng.com/item/537561","itemid":"537561","audio":[{"audioid":"537561"}],"filepath":"http://fm.ifengcdn.com/userfiles/audio02/2014/08/15/2197212-535-066-2302.mp3","filesize":"12054","isfav":0},{"title":"2014-08-14总编辑时间 何亮亮：周啸天获鲁迅文学奖有助普及旧体诗","createdTime":"2014-08-14 23:07:00","duration":1569,"order":"125216","updated_at":"1408029354","smallimgpath":"http://d.ifengimg.com/w120_h90/y0.ifengimg.com/pmop/2014/08/14/a7049458-3020-42d5-a241-992120397604.jpg","bigimgpath":"http://d.ifengimg.com/w480_h360/y0.ifengimg.com/pmop/2014/08/14/a7049458-3020-42d5-a241-992120397604.jpg","listennum":"10039","downloadnum":"465","commentnum":"0","isvideo":"1","videoplayurl":"http://ips.ifeng.com/3gs.ifeng.com/userfiles/video02/2014/08/14/2194822-280-068-2313.mp4","channelid":"1","channelid2":"0","categoryid":"1","programid":"16","programname":"总编辑时间","programlogo":"http://imgs.diantai.ifeng.com/images/programimg/f8e3eb0ff0324b38e17763ae1663050a.jpg","uradio":"0","favnum":44656,"watchingnum":"0","lastupdated_at":"1408115116","allowTrialplay":"1","source":"osmop","collectnum":"0","compere":"吕宁思","resourcenum":"645","commenturl":"http://diantai.ifeng.com/item/535695","itemid":"535695","audio":[{"audioid":"535695"}],"filepath":"http://fm.ifengcdn.com/userfiles/audio02/2014/08/14/2194822-535-066-2313.mp3","filesize":"12257","isfav":0},{"title":"2014-08-13总编辑时间 北京72座报刊亭被拆引争议 官方称系移改","createdTime":"2014-08-13 22:42:00","duration":1536,"order":"125215","updated_at":"1407941379","smallimgpath":"http://d.ifengimg.com/w120_h90/y0.ifengimg.com/pmop/2014/08/13/72364343-97b4-4404-9d47-d02b258f60bd.jpg","bigimgpath":"http://d.ifengimg.com/w480_h360/y0.ifengimg.com/pmop/2014/08/13/72364343-97b4-4404-9d47-d02b258f60bd.jpg","listennum":"9565","downloadnum":"481","commentnum":"0","isvideo":"1","videoplayurl":"http://ips.ifeng.com/3gs.ifeng.com/userfiles/video02/2014/08/13/2191687-280-068-2247.mp4","channelid":"1","channelid2":"0","categoryid":"1","programid":"16","programname":"总编辑时间","programlogo":"http://imgs.diantai.ifeng.com/images/programimg/f8e3eb0ff0324b38e17763ae1663050a.jpg","uradio":"0","favnum":44656,"watchingnum":"0","lastupdated_at":"1408115116","allowTrialplay":"1","source":"osmop","collectnum":"0","compere":"吕宁思","resourcenum":"645","commenturl":"http://diantai.ifeng.com/item/532723","itemid":"532723","audio":[{"audioid":"532723"}],"filepath":"http://fm.ifengcdn.com/userfiles/audio02/2014/08/13/2191687-535-066-2247.mp3","filesize":"12000","isfav":0},{"title":"2014-08-12总编辑时间 女子被爆在公园内放生毒蛇 自称要积德","createdTime":"2014-08-12 22:46:00","duration":1554,"order":"125214","updated_at":"1407855225","smallimgpath":"http://d.ifengimg.com/w120_h90/y0.ifengimg.com/pmop/2014/08/12/a5e229d6-2f40-40fd-872d-84b1ac5e96db.jpg","bigimgpath":"http://d.ifengimg.com/w480_h360/y0.ifengimg.com/pmop/2014/08/12/a5e229d6-2f40-40fd-872d-84b1ac5e96db.jpg","listennum":"11230","downloadnum":"470","commentnum":"0","isvideo":"1","videoplayurl":"http://ips.ifeng.com/3gs.ifeng.com/userfiles/video02/2014/08/12/2188551-280-068-2251.mp4","channelid":"1","channelid2":"0","categoryid":"1","programid":"16","programname":"总编辑时间","programlogo":"http://imgs.diantai.ifeng.com/images/programimg/f8e3eb0ff0324b38e17763ae1663050a.jpg","uradio":"0","favnum":44656,"watchingnum":"0","lastupdated_at":"1408115116","allowTrialplay":"1","source":"osmop","collectnum":"0","compere":"吕宁思","resourcenum":"645","commenturl":"http://diantai.ifeng.com/item/529945","itemid":"529945","audio":[{"audioid":"529945"}],"filepath":"http://fm.ifengcdn.com/userfiles/audio02/2014/08/12/2188551-535-066-2251.mp3","filesize":"12140","isfav":0},{"title":"2014-08-11总编辑时间 河北整治“四风” 1350人违规违纪被处理","createdTime":"2014-08-11 22:41:00","duration":1512,"order":"125213","updated_at":"1407768505","smallimgpath":"http://d.ifengimg.com/w120_h90/y0.ifengimg.com/pmop/2014/08/11/9a460bc6-d82b-4d80-bea2-45b52bc6d47a.jpg","bigimgpath":"http://d.ifengimg.com/w480_h360/y0.ifengimg.com/pmop/2014/08/11/9a460bc6-d82b-4d80-bea2-45b52bc6d47a.jpg","listennum":"14224","downloadnum":"596","commentnum":"0","isvideo":"1","videoplayurl":"http://ips.ifeng.com/3gs.ifeng.com/userfiles/video02/2014/08/11/2183834-280-068-2246.mp4","channelid":"1","channelid2":"0","categoryid":"1","programid":"16","programname":"总编辑时间","programlogo":"http://imgs.diantai.ifeng.com/images/programimg/f8e3eb0ff0324b38e17763ae1663050a.jpg","uradio":"0","favnum":44656,"watchingnum":"0","lastupdated_at":"1408115116","allowTrialplay":"1","source":"osmop","collectnum":"0","compere":"吕宁思","resourcenum":"645","commenturl":"http://diantai.ifeng.com/item/525627","itemid":"525627","audio":[{"audioid":"525627"}],"filepath":"http://fm.ifengcdn.com/userfiles/audio02/2014/08/11/2183834-535-066-2246.mp3","filesize":"11812","isfav":0},{"title":"2014-08-08总编辑时间 内地多省份普通高校学费上调 部分涨幅达50%","createdTime":"2014-08-08 23:21:00","duration":1504,"order":"125212","updated_at":"1407511768","smallimgpath":"http://d.ifengimg.com/w120_h90/y0.ifengimg.com/pmop/2014/08/08/258541de-c358-4537-84b9-4339b3960e08.jpg","bigimgpath":"http://d.ifengimg.com/w480_h360/y0.ifengimg.com/pmop/2014/08/08/258541de-c358-4537-84b9-4339b3960e08.jpg","listennum":"26797","downloadnum":"648","commentnum":"0","isvideo":"1","videoplayurl":"http://ips.ifeng.com/3gs.ifeng.com/userfiles/video02/2014/08/08/2178893-280-068-2326.mp4","channelid":"1","channelid2":"0","categoryid":"1","programid":"16","programname":"总编辑时间","programlogo":"http://imgs.diantai.ifeng.com/images/programimg/f8e3eb0ff0324b38e17763ae1663050a.jpg","uradio":"0","favnum":44656,"watchingnum":"0","lastupdated_at":"1408115116","allowTrialplay":"1","source":"osmop","collectnum":"0","compere":"吕宁思","resourcenum":"645","commenturl":"http://diantai.ifeng.com/item/521559","itemid":"521559","audio":[{"audioid":"521559"}],"filepath":"http://fm.ifengcdn.com/userfiles/audio02/2014/08/08/2178893-535-066-2326.mp3","filesize":"11750","isfav":0},{"title":"2014-08-07总编辑时间 大陆多地业主“弃房断供” 多人被银行起诉","createdTime":"2014-08-07 22:53:00","duration":1509,"order":"125211","updated_at":"1407423600","smallimgpath":"http://d.ifengimg.com/w120_h90/y0.ifengimg.com/pmop/2014/08/07/48fc4706-2919-4f5d-a67b-0e4b97a8f79b.jpg","bigimgpath":"http://d.ifengimg.com/w480_h360/y0.ifengimg.com/pmop/2014/08/07/48fc4706-2919-4f5d-a67b-0e4b97a8f79b.jpg","listennum":"28756","downloadnum":"776","commentnum":"0","isvideo":"1","videoplayurl":"http://ips.ifeng.com/3gs.ifeng.com/userfiles/video02/2014/08/07/2176405-280-068-2257.mp4","channelid":"1","channelid2":"0","categoryid":"1","programid":"16","programname":"总编辑时间","programlogo":"http://imgs.diantai.ifeng.com/images/programimg/f8e3eb0ff0324b38e17763ae1663050a.jpg","uradio":"0","favnum":44656,"watchingnum":"0","lastupdated_at":"1408115116","allowTrialplay":"1","source":"osmop","collectnum":"0","compere":"吕宁思","resourcenum":"645","commenturl":"http://diantai.ifeng.com/item/519330","itemid":"519330","audio":[{"audioid":"519330"}],"filepath":"http://fm.ifengcdn.com/userfiles/audio02/2014/08/07/2176405-535-066-2257.mp3","filesize":"11789","isfav":0},{"title":"2014-08-06总编辑时间 内地清查“裸官” 地方政府为数据“加密”","createdTime":"2014-08-06 23:01:00","duration":1480,"order":"125210","updated_at":"1407337769","smallimgpath":"http://d.ifengimg.com/w120_h90/y0.ifengimg.com/pmop/2014/08/06/81464b89-6e97-4bd1-8bb9-9bf8ef3d6de6.jpg","bigimgpath":"http://d.ifengimg.com/w480_h360/y0.ifengimg.com/pmop/2014/08/06/81464b89-6e97-4bd1-8bb9-9bf8ef3d6de6.jpg","listennum":"32467","downloadnum":"731","commentnum":"0","isvideo":"1","videoplayurl":"http://ips.ifeng.com/3gs.ifeng.com/userfiles/video02/2014/08/06/2173301-280-068-2306.mp4","channelid":"1","channelid2":"0","categoryid":"1","programid":"16","programname":"总编辑时间","programlogo":"http://imgs.diantai.ifeng.com/images/programimg/f8e3eb0ff0324b38e17763ae1663050a.jpg","uradio":"0","favnum":44656,"watchingnum":"0","lastupdated_at":"1408115116","allowTrialplay":"1","source":"osmop","collectnum":"0","compere":"吕宁思","resourcenum":"645","commenturl":"http://diantai.ifeng.com/item/516647","itemid":"516647","audio":[{"audioid":"516647"}],"filepath":"http://fm.ifengcdn.com/userfiles/audio02/2014/08/06/2173301-535-066-2306.mp3","filesize":"11562","isfav":0},{"title":"2014-08-05总编辑时间 中央巡视组：95%省份发现“地产腐败”问题","createdTime":"2014-08-05 22:59:00","duration":1533,"order":"125209","updated_at":"1407251183","smallimgpath":"http://d.ifengimg.com/w120_h90/y0.ifengimg.com/pmop/2014/08/05/86ffd5b9-248f-42a2-a0b5-48e5448d37b1.jpg","bigimgpath":"http://d.ifengimg.com/w480_h360/y0.ifengimg.com/pmop/2014/08/05/86ffd5b9-248f-42a2-a0b5-48e5448d37b1.jpg","listennum":"32797","downloadnum":"744","commentnum":"0","isvideo":"1","videoplayurl":"http://ips.ifeng.com/3gs.ifeng.com/userfiles/video02/2014/08/05/2170807-280-068-2303.mp4","channelid":"1","channelid2":"0","categoryid":"1","programid":"16","programname":"总编辑时间","programlogo":"http://imgs.diantai.ifeng.com/images/programimg/f8e3eb0ff0324b38e17763ae1663050a.jpg","uradio":"0","favnum":44656,"watchingnum":"0","lastupdated_at":"1408115116","allowTrialplay":"1","source":"osmop","collectnum":"0","compere":"吕宁思","resourcenum":"645","commenturl":"http://diantai.ifeng.com/item/514422","itemid":"514422","audio":[{"audioid":"514422"}],"filepath":"http://fm.ifengcdn.com/userfiles/audio02/2014/08/05/2170807-535-066-2303.mp3","filesize":"11976","isfav":0},{"title":"2014-08-04总编辑时间 宁夏两名厅级干部涉嫌严重违纪被组织调查","createdTime":"2014-08-04 23:14:00","duration":1538,"order":"125208","updated_at":"1407165832","smallimgpath":"http://d.ifengimg.com/w120_h90/y0.ifengimg.com/pmop/2014/08/04/b58d18e7-3657-4983-84ad-a5bf838db053.jpg","bigimgpath":"http://d.ifengimg.com/w480_h360/y0.ifengimg.com/pmop/2014/08/04/b58d18e7-3657-4983-84ad-a5bf838db053.jpg","listennum":"25765","downloadnum":"608","commentnum":"0","isvideo":"1","videoplayurl":"http://ips.ifeng.com/3gs.ifeng.com/userfiles/video02/2014/08/04/2167960-280-068-2321.mp4","channelid":"1","channelid2":"0","categoryid":"1","programid":"16","programname":"总编辑时间","programlogo":"http://imgs.diantai.ifeng.com/images/programimg/f8e3eb0ff0324b38e17763ae1663050a.jpg","uradio":"0","favnum":44656,"watchingnum":"0","lastupdated_at":"1408115116","allowTrialplay":"1","source":"osmop","collectnum":"0","compere":"吕宁思","resourcenum":"645","commenturl":"http://diantai.ifeng.com/item/511943","itemid":"511943","audio":[{"audioid":"511943"}],"filepath":"http://fm.ifengcdn.com/userfiles/audio02/2014/08/04/2167960-535-066-2321.mp3","filesize":"12015","isfav":0},{"title":"2014-08-01总编辑时间 上海市启动司法改革 探索“检察官负责制”","createdTime":"2014-08-01 22:53:00","duration":1527,"order":"125207","updated_at":"1406905240","smallimgpath":"http://d.ifengimg.com/w120_h90/y0.ifengimg.com/pmop/2014/08/01/ea6f917d-672d-44d1-ae50-62546963b049.jpg","bigimgpath":"http://d.ifengimg.com/w480_h360/y0.ifengimg.com/pmop/2014/08/01/ea6f917d-672d-44d1-ae50-62546963b049.jpg","listennum":"33124","downloadnum":"692","commentnum":"0","isvideo":"1","videoplayurl":"http://ips.ifeng.com/3gs.ifeng.com/userfiles/video02/2014/08/01/2161476-280-068-2258.mp4","channelid":"1","channelid2":"0","categoryid":"1","programid":"16","programname":"总编辑时间","programlogo":"http://imgs.diantai.ifeng.com/images/programimg/f8e3eb0ff0324b38e17763ae1663050a.jpg","uradio":"0","favnum":44656,"watchingnum":"0","lastupdated_at":"1408115116","allowTrialplay":"1","source":"osmop","collectnum":"0","compere":"吕宁思","resourcenum":"645","commenturl":"http://diantai.ifeng.com/item/505615","itemid":"505615","audio":[{"audioid":"505615"}],"filepath":"http://fm.ifengcdn.com/userfiles/audio02/2014/08/01/2161476-535-066-2258.mp3","filesize":"11929","isfav":0},{"title":"2014-07-31总编辑时间 原三鹿集团董事长田文华无期减刑至18年","createdTime":"2014-07-31 22:36:00","duration":1512,"order":"125206","updated_at":"1406817848","smallimgpath":"http://d.ifengimg.com/w120_h90/y0.ifengimg.com/pmop/2014/07/31/7985848b-fbd5-4b28-b308-e08860b2ca52.jpg","bigimgpath":"http://d.ifengimg.com/w480_h360/y0.ifengimg.com/pmop/2014/07/31/7985848b-fbd5-4b28-b308-e08860b2ca52.jpg","listennum":"42388","downloadnum":"663","commentnum":"0","isvideo":"1","videoplayurl":"http://ips.ifeng.com/3gs.ifeng.com/userfiles/video02/2014/07/31/2158630-280-068-2241.mp4","channelid":"1","channelid2":"0","categoryid":"1","programid":"16","programname":"总编辑时间","programlogo":"http://imgs.diantai.ifeng.com/images/programimg/f8e3eb0ff0324b38e17763ae1663050a.jpg","uradio":"0","favnum":44656,"watchingnum":"0","lastupdated_at":"1408115116","allowTrialplay":"1","source":"osmop","collectnum":"0","compere":"吕宁思","resourcenum":"645","commenturl":"http://diantai.ifeng.com/item/502904","itemid":"502904","audio":[{"audioid":"502904"}],"filepath":"http://fm.ifengcdn.com/userfiles/audio02/2014/07/31/2158630-535-066-2241.mp3","filesize":"11812","isfav":0},{"title":"2014-07-30总编辑时间 教育部：建立中小学及大学四级足球联赛机制","createdTime":"2014-07-30 22:40:00","duration":1570,"order":"125205","updated_at":"1406731642","smallimgpath":"http://d.ifengimg.com/w120_h90/y0.ifengimg.com/pmop/2014/07/30/40dbde00-210c-49db-b66c-2d69bd552161.jpg","bigimgpath":"http://d.ifengimg.com/w480_h360/y0.ifengimg.com/pmop/2014/07/30/40dbde00-210c-49db-b66c-2d69bd552161.jpg","listennum":"32866","downloadnum":"519","commentnum":"0","isvideo":"1","videoplayurl":"http://ips.ifeng.com/3gs.ifeng.com/userfiles/video02/2014/07/30/2155400-280-068-2244.mp4","channelid":"1","channelid2":"0","categoryid":"1","programid":"16","programname":"总编辑时间","programlogo":"http://imgs.diantai.ifeng.com/images/programimg/f8e3eb0ff0324b38e17763ae1663050a.jpg","uradio":"0","favnum":44656,"watchingnum":"0","lastupdated_at":"1408115116","allowTrialplay":"1","source":"osmop","collectnum":"0","compere":"吕宁思","resourcenum":"645","commenturl":"http://diantai.ifeng.com/item/499905","itemid":"499905","audio":[{"audioid":"499905"}],"filepath":"http://fm.ifengcdn.com/userfiles/audio02/2014/07/30/2155400-535-066-2244.mp3","filesize":"12265","isfav":0},{"title":"2014-07-29总编辑时间 中共中央决定对周永康严重违纪问题立案审查 ","createdTime":"2014-07-29 22:36:00","duration":1528,"order":"125204","updated_at":"1406645074","smallimgpath":"http://d.ifengimg.com/w120_h90/y0.ifengimg.com/pmop/2014/07/29/d090588c-5c5b-41ff-b14f-e03a93e2681b.jpg","bigimgpath":"http://d.ifengimg.com/w480_h360/y0.ifengimg.com/pmop/2014/07/29/d090588c-5c5b-41ff-b14f-e03a93e2681b.jpg","listennum":"47368","downloadnum":"914","commentnum":"0","isvideo":"1","videoplayurl":"http://ips.ifeng.com/3gs.ifeng.com/userfiles/video02/2014/07/29/2151763-280-068-2241.mp4","channelid":"1","channelid2":"0","categoryid":"1","programid":"16","programname":"总编辑时间","programlogo":"http://imgs.diantai.ifeng.com/images/programimg/f8e3eb0ff0324b38e17763ae1663050a.jpg","uradio":"0","favnum":44656,"watchingnum":"0","lastupdated_at":"1408115116","allowTrialplay":"1","source":"osmop","collectnum":"0","compere":"吕宁思","resourcenum":"645","commenturl":"http://diantai.ifeng.com/item/496498","itemid":"496498","audio":[{"audioid":"496498"}],"filepath":"http://fm.ifengcdn.com/userfiles/audio02/2014/07/29/2151763-535-066-2241.mp3","filesize":"11937","isfav":0},{"title":"2014-07-28总编辑时间 郭美美疑供出“干爹” 传王军被警方带走","createdTime":"2014-07-28 22:47:00","duration":1551,"order":"125203","updated_at":"1406559268","smallimgpath":"http://d.ifengimg.com/w120_h90/y0.ifengimg.com/pmop/2014/07/28/15d7ef5b-4528-4fd3-8fc6-af53e681ca4c.jpg","bigimgpath":"http://d.ifengimg.com/w480_h360/y0.ifengimg.com/pmop/2014/07/28/15d7ef5b-4528-4fd3-8fc6-af53e681ca4c.jpg","listennum":"430993","downloadnum":"943","commentnum":"0","isvideo":"1","videoplayurl":"http://ips.ifeng.com/3gs.ifeng.com/userfiles/video02/2014/07/28/2148346-280-068-2251.mp4","channelid":"1","channelid2":"0","categoryid":"1","programid":"16","programname":"总编辑时间","programlogo":"http://imgs.diantai.ifeng.com/images/programimg/f8e3eb0ff0324b38e17763ae1663050a.jpg","uradio":"0","favnum":44656,"watchingnum":"0","lastupdated_at":"1408115116","allowTrialplay":"1","source":"osmop","collectnum":"0","compere":"吕宁思","resourcenum":"645","commenturl":"http://diantai.ifeng.com/item/493575","itemid":"493575","audio":[{"audioid":"493575"}],"filepath":"","filesize":"12109","isfav":0},{"title":"2014-07-25总编辑时间 内地多地政府大楼闲置 官方回应“风声紧”","createdTime":"2014-07-25 23:15:00","duration":1548,"order":"125202","updated_at":"1406301876","smallimgpath":"http://d.ifengimg.com/w120_h90/y0.ifengimg.com/pmop/2014/07/25/cf5cb1b6-c7cc-4004-b126-0ced342c17a5.jpg","bigimgpath":"http://d.ifengimg.com/w480_h360/y0.ifengimg.com/pmop/2014/07/25/cf5cb1b6-c7cc-4004-b126-0ced342c17a5.jpg","listennum":"45028","downloadnum":"689","commentnum":"0","isvideo":"1","videoplayurl":"http://ips.ifeng.com/3gs.ifeng.com/userfiles/video02/2014/07/25/2142793-280-068-2320.mp4","channelid":"1","channelid2":"0","categoryid":"1","programid":"16","programname":"总编辑时间","programlogo":"http://imgs.diantai.ifeng.com/images/programimg/f8e3eb0ff0324b38e17763ae1663050a.jpg","uradio":"0","favnum":44656,"watchingnum":"0","lastupdated_at":"1408115116","allowTrialplay":"1","source":"osmop","collectnum":"0","compere":"吕宁思","resourcenum":"645","commenturl":"http://diantai.ifeng.com/item/488625","itemid":"488625","audio":[{"audioid":"488625"}],"filepath":"http://fm.ifengcdn.com/userfiles/audio02/2014/07/25/2142793-535-066-2320.mp3","filesize":"12093","isfav":0},{"title":"2014-07-24总编辑时间 山西纪委副书记杨森林被查","createdTime":"2014-07-24 23:12:00","duration":1586,"order":"125201","updated_at":"1406215122","smallimgpath":"http://d.ifengimg.com/w120_h90/y0.ifengimg.com/pmop/2014/07/24/b22a3c79-1679-4d0e-873c-d046293eafb7.jpg","bigimgpath":"http://d.ifengimg.com/w480_h360/y0.ifengimg.com/pmop/2014/07/24/b22a3c79-1679-4d0e-873c-d046293eafb7.jpg","listennum":"40402","downloadnum":"594","commentnum":"0","isvideo":"1","videoplayurl":"http://ips.ifeng.com/3gs.ifeng.com/userfiles/video02/2014/07/24/2139272-280-068-2315.mp4","channelid":"1","channelid2":"0","categoryid":"1","programid":"16","programname":"总编辑时间","programlogo":"http://imgs.diantai.ifeng.com/images/programimg/f8e3eb0ff0324b38e17763ae1663050a.jpg","uradio":"0","favnum":44656,"watchingnum":"0","lastupdated_at":"1408115116","allowTrialplay":"1","source":"osmop","collectnum":"0","compere":"吕宁思","resourcenum":"645","commenturl":"http://diantai.ifeng.com/item/485429","itemid":"485429","audio":[{"audioid":"485429"}],"filepath":"http://fm.ifengcdn.com/userfiles/audio02/2014/07/24/2139272-535-066-2315.mp3","filesize":"12382","isfav":0},{"title":"2014-07-23总编辑时间 台客机迫降澎湖西溪村失败 致47人死亡11伤","createdTime":"2014-07-23 23:01:00","duration":1563,"order":"125200","updated_at":"1406128107","smallimgpath":"http://d.ifengimg.com/w120_h90/y0.ifengimg.com/pmop/2014/07/23/f17e1052-b87a-454e-a9e1-8b00114e06af.jpg","bigimgpath":"http://d.ifengimg.com/w480_h360/y0.ifengimg.com/pmop/2014/07/23/f17e1052-b87a-454e-a9e1-8b00114e06af.jpg","listennum":"36631","downloadnum":"495","commentnum":"0","isvideo":"1","videoplayurl":"http://ips.ifeng.com/3gs.ifeng.com/userfiles/video02/2014/07/23/2135367-280-068-2305.mp4","channelid":"1","channelid2":"0","categoryid":"1","programid":"16","programname":"总编辑时间","programlogo":"http://imgs.diantai.ifeng.com/images/programimg/f8e3eb0ff0324b38e17763ae1663050a.jpg","uradio":"0","favnum":44656,"watchingnum":"0","lastupdated_at":"1408115116","allowTrialplay":"1","source":"osmop","collectnum":"0","compere":"吕宁思","resourcenum":"645","commenturl":"http://diantai.ifeng.com/item/481842","itemid":"481842","audio":[{"audioid":"481842"}],"filepath":"http://fm.ifengcdn.com/userfiles/audio02/2014/07/23/2135367-535-066-2305.mp3","filesize":"12210","isfav":0},{"title":"2014-07-22总编辑时间 公安部部署缉捕在逃境外经济犯罪嫌犯人行动","createdTime":"2014-07-22 23:08:00","duration":1451,"order":"125199","updated_at":"1406042118","smallimgpath":"http://d.ifengimg.com/w120_h90/y0.ifengimg.com/pmop/2014/07/22/8553680b-68b4-46c6-bc18-cb11927133ae.jpg","bigimgpath":"http://d.ifengimg.com/w480_h360/y0.ifengimg.com/pmop/2014/07/22/8553680b-68b4-46c6-bc18-cb11927133ae.jpg","listennum":"38536","downloadnum":"615","commentnum":"0","isvideo":"1","videoplayurl":"http://ips.ifeng.com/3gs.ifeng.com/userfiles/video02/2014/07/22/2132194-280-068-2312.mp4","channelid":"1","channelid2":"0","categoryid":"1","programid":"16","programname":"总编辑时间","programlogo":"http://imgs.diantai.ifeng.com/images/programimg/f8e3eb0ff0324b38e17763ae1663050a.jpg","uradio":"0","favnum":44656,"watchingnum":"0","lastupdated_at":"1408115116","allowTrialplay":"1","source":"osmop","collectnum":"0","compere":"吕宁思","resourcenum":"645","commenturl":"http://diantai.ifeng.com/item/479287","itemid":"479287","audio":[{"audioid":"479287"}],"filepath":"http://fm.ifengcdn.com/userfiles/audio02/2014/07/22/2132194-535-066-2312.mp3","filesize":"11335","isfav":0},{"title":"2014-07-21总编辑时间 中央巡视组进驻体总 足管中心进入巡视名单","createdTime":"2014-07-21 23:36:00","duration":1583,"order":"125198","updated_at":"1405957366","smallimgpath":"http://d.ifengimg.com/w120_h90/y0.ifengimg.com/pmop/2014/07/21/cfb1cca9-8437-44df-aa8e-a628334c00d4.jpg","bigimgpath":"http://d.ifengimg.com/w480_h360/y0.ifengimg.com/pmop/2014/07/21/cfb1cca9-8437-44df-aa8e-a628334c00d4.jpg","listennum":"40216","downloadnum":"637","commentnum":"0","isvideo":"1","videoplayurl":"http://ips.ifeng.com/3gs.ifeng.com/userfiles/video02/2014/07/21/2128249-280-068-2339.mp4","channelid":"1","channelid2":"0","categoryid":"1","programid":"16","programname":"总编辑时间","programlogo":"http://imgs.diantai.ifeng.com/images/programimg/f8e3eb0ff0324b38e17763ae1663050a.jpg","uradio":"0","favnum":44656,"watchingnum":"0","lastupdated_at":"1408115116","allowTrialplay":"1","source":"osmop","collectnum":"0","compere":"吕宁思","resourcenum":"645","commenturl":"http://diantai.ifeng.com/item/475576","itemid":"475576","audio":[{"audioid":"475576"}],"filepath":"http://fm.ifengcdn.com/userfiles/audio02/2014/07/21/2128249-535-066-2339.mp3","filesize":"12367","isfav":0}]}}